[{"title":"Windows实用软件-压缩软件","url":"/2020/03/06/Windows实用软件-压缩软件/"},{"title":"Windows实用软件-音乐下载","url":"/2020/03/06/Windows实用软件-音乐下载/"},{"title":"实验1第一题-文件操作","url":"/2020/03/02/实验1第一题-文件操作/"},{"title":"实验2第1题-工资","url":"/2020/03/15/实验2第1题-工资/"},{"title":"实验2第2题-工资","url":"/2020/03/15/实验2第2题-工资/"},{"title":"实验2第3题-图书借阅","url":"/2020/03/15/实验2第3题-图书借阅/"},{"title":"实验1第三题-陕西十大怪","url":"/2020/03/02/实验1第三题-陕西十大怪/"},{"title":"实验1第二题-印章管理办法","url":"/2020/03/02/实验1第二题-印章管理办法/"},{"title":"Windows下Office2010_2016安装及破解","url":"/2020/03/01/Windows下Office2010_2016安装及破解/"}]